[{"ID":3,"Title":"Math Homework","Description":"kinda hard","IsCompleted":false,"IsStarred":false,"IsReminderOn":true,"IsAdvanceReminderOn":false,"BeginDateTime":null,"EndDateTime":"2020-12-17T22:39:08.3296329+08:00","CreationDateTime":"0001-01-01T00:00:00","Tags":null},{"ID":4,"Title":"Read Pro Angular 6","Description":"","IsCompleted":true,"IsStarred":false,"IsReminderOn":true,"IsAdvanceReminderOn":true,"BeginDateTime":"2020-12-17T22:10:08.3296543+08:00","EndDateTime":"2020-12-17T23:09:08.3296552+08:00","CreationDateTime":"0001-01-01T00:00:00","Tags":null},{"ID":5,"Title":"Call someone hello hello","Description":"I forgot who it was ;p","IsCompleted":false,"IsStarred":true,"IsReminderOn":false,"IsAdvanceReminderOn":false,"BeginDateTime":null,"EndDateTime":null,"CreationDateTime":"0001-01-01T00:00:00","Tags":null},{"ID":6,"Title":"Review electronic","Description":"prepare for the test","IsCompleted":false,"IsStarred":true,"IsReminderOn":false,"IsAdvanceReminderOn":false,"BeginDateTime":null,"EndDateTime":null,"CreationDateTime":"0001-01-01T00:00:00","Tags":null},{"ID":7,"Title":"Program","Description":"Angular + JS","IsCompleted":true,"IsStarred":true,"IsReminderOn":false,"IsAdvanceReminderOn":false,"BeginDateTime":null,"EndDateTime":null,"CreationDateTime":"0001-01-01T00:00:00","Tags":null},{"ID":8,"Title":"electronic test","Description":"1-1:RC coupler","IsCompleted":false,"IsStarred":true,"IsReminderOn":false,"IsAdvanceReminderOn":false,"BeginDateTime":null,"EndDateTime":null,"CreationDateTime":"0001-01-01T00:00:00","Tags":null},{"ID":9,"Title":"Math test","Description":"test ?! again ?!","IsCompleted":true,"IsStarred":false,"IsReminderOn":true,"IsAdvanceReminderOn":false,"BeginDateTime":null,"EndDateTime":"2020-12-18T22:09:08.3296689+08:00","CreationDateTime":"0001-01-01T00:00:00","Tags":null},{"ID":0,"Title":null,"Description":"","IsCompleted":false,"IsStarred":false,"IsReminderOn":false,"IsAdvanceReminderOn":false,"BeginDateTime":null,"EndDateTime":null,"CreationDateTime":"0001-01-01T00:00:00","Tags":null}]